process_time_azure_devops/__init__.py
process_time_azure_devops/__main__.py
process_time_azure_devops/arts/__init__.py
process_time_azure_devops/arts/process_time_logo.py
process_time_azure_devops/flows/Flow.py
process_time_azure_devops/flows/GitFlow.py
process_time_azure_devops/flows/TrunkBasedFlow.py
process_time_azure_devops/flows/__init__.py
process_time_azure_devops/flows/get_flow.py
process_time_azure_devops/models/ArgumentParseResult.py
process_time_azure_devops/models/JsonResult.py
process_time_azure_devops/models/__init__.py
process_time_azure_devops/parsers/__init__.py
process_time_azure_devops/parsers/find_pr.py
process_time_azure_devops/parsers/get_first_commit_date.py
process_time_azure_devops/parsers/get_last_attempt_to_deliver.py
process_time_azure_devops-0.3.0.dist-info/METADATA
process_time_azure_devops-0.3.0.dist-info/WHEEL
process_time_azure_devops-0.3.0.dist-info/licenses/LICENSE
process_time_azure_devops-0.3.0.dist-info/RECORD
